aguirre/__init__.py
aguirre/py.typed
aguirre/util.py
aguirre/integrations/__init__.py
aguirre/integrations/django.py
aguirre/integrations/flask.py
aguirre/integrations/quart.py
aguirre-0.2.1.dist-info/licenses/LICENCE.txt
aguirre-0.2.1.dist-info/METADATA
aguirre-0.2.1.dist-info/WHEEL
aguirre-0.2.1.dist-info/top_level.txt
aguirre-0.2.1.dist-info/RECORD
