Metadata-Version: 2.4
Name: aguirre
Version: 0.2.1
Summary: Let Python webservers self-host JS/CSS/etc assets like unpkg does
Home-page: https://github.com/pscl4rke/aguirre
Author: P. S. Clarke
Author-email: aguirre@pscl4rke.net
License: cf:licence
Project-URL: Source Code, https://github.com/pscl4rke/aguirre
Project-URL: Issues, https://github.com/pscl4rke/aguirre/issues
Project-URL: Licence, https://github.com/pscl4rke/aguirre/blob/master/LICENCE.txt
Classifier: Development Status :: 4 - Beta
Classifier: Programming Language :: Python :: 3.8
Classifier: Programming Language :: Python :: 3.9
Classifier: Programming Language :: Python :: 3.10
Classifier: Programming Language :: Python :: 3.11
Classifier: Programming Language :: Python :: 3.12
Classifier: Programming Language :: Python :: 3.13
Classifier: Topic :: Internet :: WWW/HTTP
Requires-Python: >=3.8
License-File: LICENCE.txt
Provides-Extra: testing
Requires-Dist: coverage; extra == "testing"
Requires-Dist: django; extra == "testing"
Requires-Dist: django-stubs; extra == "testing"
Requires-Dist: flask; extra == "testing"
Requires-Dist: mypy; extra == "testing"
Requires-Dist: pyroma; extra == "testing"
Requires-Dist: quart; extra == "testing"
Dynamic: license-file
